messy2sql
tests
