Metadata-Version: 1.1
Name: messy2sql
Version: 0.1.0a8
Summary: Convert messytables types to SQL create/insert statements
Home-page: http://publicfragments.org
Author: Alexander J Fink
Author-email: alexanderjfink@gmail.com
License: MIT
Platform: UNKNOWN
Classifier: Development Status :: 2 - Pre-Alpha
Classifier: Intended Audience :: Developers
Classifier: License :: OSI Approved :: MIT License
Classifier: Operating System :: OS Independent
Classifier: Programming Language :: Python
